Workbook

Sheet Raw Data
A1: Date | B1: Product | C1: Category | D1: Region | E1: Sales_Rep | F1: Units_Sold | G1: Unit_Price | H1: Revenue | I1: Cost | J1: Profit
A2: 45446 | B2: USB-C Hub | C2: Peripherals | D2: Central | E2: Anna Kim | F2: 21 | G2: 54.16 | H2: 1137.3 | I2: 776.44 | J2: 360.86
A3: 45447 | B3: Webcam HD | C3: Accessories | D3: East | E3: Mike Chen | F3: 19 | G3: 108.61 | H3: 2063.56 | I3: 1532.25 | J3: 531.31
A4: 45449 | B4: Gaming Mouse | C4: Electronics | D4: East | E4: Emma Davis | F4: 26 | G4: 83.08 | H4: 2160.13 | I4: 1550.16 | J4: 609.97
A5: 45449 | B5: Gaming Mouse | C5: Storage | D5: South | E5: Mike Chen | F5: 23 | G5: 73.36 | H5: 1687.22 | I5: 1260.91 | J5: 426.31
A6: 45450 | B6: Wireless Keyboard | C6: Storage | D6: East | E6: James Wilson | F6: 20 | G6: 93.99 | H6: 1879.87 | I6: 1227.27 | J6: 652.6
A7: 45451 | B7: Portable SSD | C7: Storage | D7: South | E7: Mike Chen | F7: 19 | G7: 147.59 | H7: 2804.24 | I7: 1900.45 | J7: 903.79
A8: 45451 | B8: Gaming Mouse | C8: Electronics | D8: South | E8: Sarah Lee | F8: 23 | G8: 80.19 | H8: 1844.45 | I8: 1098 | J8: 746.45
A9: 45452 | B9: Smartphone X | C9: Electronics | D9: Central | E9: Anna Kim | F9: 26 | G9: 918.09 | H9: 23870.42 | I9: 16303.67 | J9: 7566.75
A10: 45462 | B10: Webcam HD | C10: Peripherals | D10: South | E10: Emma Davis | F10: 17 | G10: 129.9 | H10: 2208.24 | I10: 1307.57 | J10: 900.67
A11: 45464 | B11: Smartphone X | C11: Storage | D11: West | E11: John Smith | F11: 20 | G11: 915.06 | H11: 18301.16 | I11: 10350.17 | J11: 7951
A12: 45465 | B12: Webcam HD | C12: Accessories | D12: Central | E12: Anna Kim | F12: 24 | G12: 111.15 | H12: 2667.6 | I12: 1484.53 | J12: 1183.07
A13: 45465 | B13: Smartphone X | C13: Mobile | D13: South | E13: Emma Davis | F13: 18 | G13: 817.34 | H13: 14712.11 | I13: 9830.32 | J13: 4881.79
... A451: 46022 | B451: Monitor 4K | C451: Electronics | D451: Central | E451: Emma Davis | F451: 48 | G451: 378.64 | H451: 18174.56 | I451: 10084.71 | J451: 8089.86

Sheet Calculations
A1: MONTHLY SALES SUMMARY | H1: SALES BY CATEGORY
A2: Month | B2: Total Revenue | C2: Total Profit | D2: Units Sold | E2: Profit Margin % | F2: Forecast Revenue | H2: Category | I2: Revenue | J2: Profit | K2: Units | L2: % of Total
A3: 2024-06 | B3: 112294.38 | C3: 38891.45 | D3: 363 | E3: 34.63 | H3: Accessories | I3: 931802.24 | J3: 316269.07 | K3: 2146 | L3: =I3/SUM($I$3:$I$7)
A4: 2024-07 | B4: 148002.43 | C4: 53351.19 | D4: 360 | E4: 36.05 | H4: Electronics | I4: 1048340 | J4: 379739.04 | K4: 2536 | L4: =I4/SUM($I$3:$I$7)
A5: 2024-08 | B5: 195362.99 | C5: 65561.59 | D5: 547 | E5: 33.56 | H5: Mobile | I5: 921725.99 | J5: 308382.07 | K5: 2472 | L5: =I5/SUM($I$3:$I$7)
A6: 2024-09 | B6: 115702.96 | C6: 42064.27 | D6: 406 | E6: 36.36 | H6: Peripherals | I6: 1263598.2 | J6: 440685.8 | K6: 2757 | L6: =I6/SUM($I$3:$I$7)
A7: 2024-10 | B7: 266857.19 | C7: 93061.4 | D7: 669 | E7: 34.87 | H7: Storage | I7: 1035733.7 | J7: 363860.29 | K7: 2784 | L7: =I7/SUM($I$3:$I$7)
A8: 2024-11 | B8: 185070.67 | C8: 67256.35 | D8: 580 | E8: 36.34
A9: 2024-12 | B9: 239703.55 | C9: 85705.7 | D9: 528 | E9: 35.75
A10: 2025-01 | B10: 180950.29 | C10: 60762.3 | D10: 357 | E10: 33.58
A11: 2025-02 | B11: 243697.05 | C11: 89217.21 | D11: 634 | E11: 36.61
A12: 2025-03 | B12: 590303.1 | C12: 200494.77 | D12: 1058 | E12: 33.96
A13: 2025-04 | B13: 319734.04 | C13: 114003.2 | D13: 745 | E13: 35.66
A14: 2025-05 | B14: 296299.79 | C14: 94044.4 | D14: 890 | E14: 31.74
A15: 2025-06 | B15: 459855.77 | C15: 165498.09 | D15: 1037 | E15: 35.99 | H15: SALES BY REGION
A16: 2025-07 | B16: 260028.09 | C16: 90022.35 | D16: 680 | E16: 34.62 | H16: Region | I16: Revenue | J16: Profit | K16: Profit Margin % | L16: Growth %
A17: 2025-08 | B17: 387756.75 | C17: 144322.39 | D17: 852 | E17: 37.22 | H17: Central | I17: 985326.43 | J17: 334925.21 | K17: =J17/I17*100
A18: 2025-09 | B18: 343103.94 | C18: 119482.25 | D18: 780 | E18: 34.82 | H18: East | I18: 1320008.5 | J18: 457696.38 | K18: =J18/I18*100
A19: 2025-10 | B19: 344132.05 | C19: 113940.1 | D19: 794 | E19: 33.11 | H19: North | I19: 831110.32 | J19: 287307.23 | K19: =J19/I19*100
A20: 2025-11 | B20: 269472.13 | C20: 93987.32 | D20: 640 | E20: 34.88 | H20: South | I20: 1056145.9 | J20: 363448.06 | K20: =J20/I20*100
A21: 2025-12 | B21: 242872.93 | C21: 77269.94 | D21: 775 | E21: 31.81 | H21: West | I21: 1008608.9 | J21: 365559.39 | K21: =J21/I21*100
A22: FORECAST (Next 6 Months)
A23: NaT | B23: =IFERROR(FORECAST.ETS(A23, Calculations!$B$3:Calculations!$B$21, Calculations!$A$3:Calculations!$A$21, 1, 1), 0) | F23: =IFERROR(FORECAST.ETS.CONFINT(A23, Calculations!$B$3:Calculations!$B$21, Calculations!$A$3:Calculations!$A$21, 0.95), 0)
A24: NaT | B24: =IFERROR(FORECAST.ETS(A24, Calculations!$B$3:Calculations!$B$21, Calculations!$A$3:Calculations!$A$21, 1, 1), 0) | F24: =IFERROR(FORECAST.ETS.CONFINT(A24, Calculations!$B$3:Calculations!$B$21, Calculations!$A$3:Calculations!$A$21, 0.95), 0)
A25: NaT | B25: =IFERROR(FORECAST.ETS(A25, Calculations!$B$3:Calculations!$B$21, Calculations!$A$3:Calculations!$A$21, 1, 1), 0) | F25: =IFERROR(FORECAST.ETS.CONFINT(A25, Calculations!$B$3:Calculations!$B$21, Calculations!$A$3:Calculations!$A$21, 0.95), 0)
A26: NaT | B26: =IFERROR(FORECAST.ETS(A26, Calculations!$B$3:Calculations!$B$21, Calculations!$A$3:Calculations!$A$21, 1, 1), 0) | F26: =IFERROR(FORECAST.ETS.CONFINT(A26, Calculations!$B$3:Calculations!$B$21, Calculations!$A$3:Calculations!$A$21, 0.95), 0)
A27: NaT | B27: =IFERROR(FORECAST.ETS(A27, Calculations!$B$3:Calculations!$B$21, Calculations!$A$3:Calculations!$A$21, 1, 1), 0) | F27: =IFERROR(FORECAST.ETS.CONFINT(A27, Calculations!$B$3:Calculations!$B$21, Calculations!$A$3:Calculations!$A$21, 0.95), 0)
A28: NaT | B28: =IFERROR(FORECAST.ETS(A28, Calculations!$B$3:Calculations!$B$21, Calculations!$A$3:Calculations!$A$21, 1, 1), 0) | F28: =IFERROR(FORECAST.ETS.CONFINT(A28, Calculations!$B$3:Calculations!$B$21, Calculations!$A$3:Calculations!$A$21, 0.95), 0)
H30: TOP 5 PRODUCTS
H31: Product | I31: Revenue | J31: Units | K31: Avg Price
H32: Laptop Pro | I32: 1584926.9 | J32: 1315 | K32: 1203.25
H33: Smartphone X | I33: 1310772.2 | J33: 1452 | K33: 901.63
H34: Tablet Air | I34: 861859.9 | J34: 1451 | K34: 595.33
H35: Monitor 4K | I35: 549661.71 | J35: 1381 | K35: 398.38
H36: Noise Headphones | I36: 284024.26 | J36: 1130 | K36: 251.08

Sheet Dashboard
A1: SALES DASHBOARD - Interactive Analytics & Predictions
A3: KEY PERFORMANCE INDICATORS | D3: PREDICTIONS (Next 6 Months)
A4: Total Revenue | D4: Month | E4: Forecast | F4: Confidence ±
A5: =SUM(Calculations!B3:B28) | D5: =Calculations!A23 | E5: =Calculations!B23 | F5: =Calculations!F23
A6: Total Profit | D6: =Calculations!A24 | E6: =Calculations!B24 | F6: =Calculations!F24
A7: =SUM(Calculations!C3:C28) | D7: =Calculations!A25 | E7: =Calculations!B25 | F7: =Calculations!F25
A8: Avg Profit Margin | D8: =Calculations!A26 | E8: =Calculations!B26 | F8: =Calculations!F26
A9: =TEXT(AVERAGE(Calculations!E3:E28)/100,"0.0%") | D9: =Calculations!A27 | E9: =Calculations!B27 | F9: =Calculations!F27
A10: Total Units | D10: =Calculations!A28 | E10: =Calculations!B28 | F10: =Calculations!F28
A11: =SUM(Calculations!D3:D28)
D14: AUTO-GENERATED INSIGHTS
D15: ="Top Region: " & INDEX(Calculations!H17:H21, MATCH(MAX(Calculations!I17:I21), Calculations!I17:I21, 0)) & " (" & TEXT(MAX(Calculations!I17:I21)/SUM(Calculations!I17:I21),"0%") & " of revenue)"
D16: ="Top Category: " & INDEX(Calculations!H3:H7, MATCH(MAX(Calculations!I3:I7), Calculations!I3:I7, 0)) & " (" & TEXT(MAX(Calculations!I3:I7)/SUM(Calculations!I3:I7),"0%") & " of revenue)"
D17: ="Best Profit Margin: " & INDEX(Calculations!H17:H21, MATCH(MAX(Calculations!K17:K21), Calculations!K17:K21, 0)) & " (" & TEXT(MAX(Calculations!K17:K21)/100,"0.0%") & ")"
D18: ="Forecast Growth: " & TEXT((Calculations!B33/Calculations!B28-1),"0.0%") & " (next month vs last month)"
D19: ="Total Products Analyzed: " & COUNTA(UNIQUE(RawData!B:B))-1
